pluggen/__init__.py
pluggen/plugin.py
pluggen-1.0.0b3.dist-info/METADATA
pluggen-1.0.0b3.dist-info/WHEEL
pluggen-1.0.0b3.dist-info/top_level.txt
pluggen-1.0.0b3.dist-info/RECORD
