Metadata-Version: 2.1
Name: pluggen
Version: 1.0.0b3
Summary: A module for plugin discovery and instantiation
Author-email: Staffan Thomén <staffan@thomen.fi>
License: BSD 3-Clause License
Project-URL: Homepage, https://git.shangtai.net/staffan/pluggen
Keywords: plugins,discovery
Classifier: Development Status :: 4 - Beta
Classifier: Programming Language :: Python :: 3
